{"title": "        Purina Tidy Cats Clumping Cat Litter, Free & Clean Unscented Multi Cat Litter - 38 lb. Box       ", "url": "https://www.amazon.com/Purina-Tidy-Cats-Clumping-Unscented/dp/B0CGJG25PV/ref=sxin_16_pa_sp_search_thematic-asin_sspa?c=ts&content-id=amzn1.sym.d3ed3243-8938-4d2a-88bf-7da70bc508a3%3Aamzn1.sym.d3ed3243-8938-4d2a-88bf-7da70bc508a3&cv_ct_cx=Cat+Litter+%26+Housebreaking&keywords=Cat+Litter+%26+Housebreaking&pd_rd_i=B0CGJG25PV&pd_rd_r=f0697552-5967-48ec-bade-957e72d54ca4&pd_rd_w=KubKw&pd_rd_wg=wKydA&pf_rd_p=d3ed3243-8938-4d2a-88bf-7da70bc508a3&pf_rd_r=TPAGS526SKZP8GHBP98W&qid=1740848267&s=pet-supplies&sbo=RZvfv%2F%2FHxDF%2BO5021pAnSA%3D%3D&sr=1-2-baa1f287-65d3-41a3-a655-8bbba0531537-spons&ts_id=2975296011&sp_csd=d2lkZ2V0TmFtZT1zcF9zZWFyY2hfdGhlbWF0aWM&psc=1", "tags": ["Pet Supplies", "Cats", "Litter & Housebreaking", "Litter"], "image": "https://m.media-amazon.com/images/I/71aRxioMgaL._AC_SX679_.jpg", "description": ["Fill your cats' litter boxes with Purina Tidy Cats Free and Clean Unscented Clumping Multi Cat litter, and provide them with uncompromising odor control. This charcoal litter solution is free of fragrances and dyes, making it an ideal option for cats and pet parents who prefer unscented cat litter. Guaranteed odor control in the litter helps you maintain a fresh-smelling home for up to 10 days when used as directed, and our low dust clumping cat litter formula helps provide a clean pour. We formulate this clay unscented kitty litter with activated odor control charcoal to help absorb odors, and it forms tight, strong clumps for easy scooping. Let your cats paw their way through our low dust cat litter made with natural clay and activated charcoal, and watch as they purr in appreciation after each use. This Purina Tidy Cats odor control litter is backed by 70 years of litter expertise."]}